{
	"finance":{
			"data":{
					"Получено":"65000",
					"Приход":[
						{"Дата":"10.03.2020",
						"Автомобили":[
							{"Грузоподъемность":"5000","Марка":"DUFF","Мощность":"220л/с"}
							],
						"Сумма":"123000"},
						{"Дата":"20.11.2020",
						"Автомобили":[
							{"Грузоподъемность":"3000","Марка":"ГазЕль","Мощность":"140л/с"}
							],
						"Сумма":"83000"}
						],
					"Дата":"12.05.2021",
					"Потрачено":"75000",
					"Расход":[
						{"Дата":"15.04.2020",
						"Автомобили":[
							{"Грузоподъемность":"25000","Марка":"КамАЗ","Мощность":"800л/с"},
							{"Грузоподъемность":"20000","Марка":"МАЗ","Мощность":"700л/с"},
							{"Грузоподъемность":"2500","Марка":"Соболь","Мощность":"200л/с"}
							],
						"Сумма":"88000"}],
					"ФИО":"Семен Семенович Иванов"
					}
				},
	"autopark":{
			"code":"autostate",
			"data":{
				"Дата":"12.05.2020",
				"Итого":"120520",
				"Операции":[
						{"Дата":"15.04.2020","Сумма":"25000"},
						{"Дата":"01.11.2020","Сумма":"20000"},
						{"Дата":"15.02.2021","Сумма":"2000"}
					]
				}
		},
	"request":{
			"data":[
				{"ID":86,
				"Вес":20,
				"Водитель":"Вечканов Владимир Николаевич",
				"Груз":"Продукты питания",
				"ДатаЗаявки":"2021-03-03T16:51:52",
				"ДатаЗаявкиКонтрагента":"2021-02-11T00:00:00",
				"ДеталиПеревозки":[
						{"Адрес":"Самарская обл. Волжский р-н п.Стройкерамика ул.Производственная строение 8 ООО\"Кухмастер\"",
						"Вес":20,
						"Вид":"Погрузка",
						"ВремяПо":"0001-01-01T16:00:00",
						"ВремяС":"0001-01-01T09:00:00",
						"Город":"Стройкерамика пгт, Самарская обл",
						"Груз":"Продукты питания",
						"Дата":"2021-03-04T00:00:00",
						"СпособПогрузки":"Задняя",
						"Упаковка":"Паллет"},
						{"Адрес":"Московская обл.г.Коломенский р-н с.Парфентьево промышленная зона,строение 1 АО\"Тандер\"",
						"Вес":20,"Вид":"Разгрузка",
						"ВремяПо":"0001-01-01T00:00:00",
						"ВремяС":"0001-01-01T00:00:00",
						"Город":"Парфентьево с, Коломна г, Московская обл",
						"Груз":"Продукты питания",
						"Дата":"2021-03-06T00:00:00",
						"СпособПогрузки":"Задняя",
						"Упаковка":"Паллет"}
					],
				"Заказчик":"КУХМАСТЕР ООО",
				"КонечнаяДатаОплаты":"0001-01-01T00:00:00",
				"КонтактноеЛицо":"Бехтин Александр",
				"КонтактноеЛицоПеревозчика":" Екатерина",
				"Маршрут":"Стройкерамика пгт, Самарская обл - Парфентьево с, Коломна г, Московская обл",
				"НомерЗаявки":"0000000913",
				"НомерЗаявкиКонтрагента":"000000926",
				"ОтсрочкаПлатежа":15,"Перевозчик":"ТрансЛогистик ООО",
				"Статус":"Оформление",
				"СтатусОплаты":false,
				"Стоимость":38000,
				"ТелефонВодителя":"8-903-712-5630",
				"ТелефонКонтактногоЛица":"89397193060",
				"ТелефонКонтактногоЛицаПеревозчика":"+7 (919) 998 21 95",
				"Транспорт":"МЕРСЕДЕС Р851РО799 ПП ЕН925377",
				"УсловиеПеревозчика":"По оригиналам документов: Счет, акт и счет-фактура (либо УПД), накладных (ТН, ТТН, CMR) 15 б.д. СТРОГО при соблюдении п.5.16",
				"УсловияЗаказчика":"Оригиналы 15 б\/д: Заявка, Счет, 2 экз Акт, ТН,Торг-12,С-Ф\/УПД,Доверенность на водителя с отметками",
				"Файлы":[
						{"Имя":"doc04198820210303175101","Расширение":"pdf"},
						{"Имя":"doc03792120210303190455","Расширение":"pdf"},
						{"Имя":"doc03792320210303203848","Расширение":"pdf"},
						{"Имя":"Руководство пользователя SB2109 BT рус","Расширение":"pdf"},
						{"Имя":"3.49. Работа с файлами __ Библиотека стандартных подсистем 3.1.2. Документация","Расширение":"pdf"}
						],
				"ФормаОплатыЗаказчика":"Безналичный расчет в т.ч. НДС (20%)",
				"ФормаОплатыПеревозчика":"Безналичный расчет НДС не облагается",
				"ЭтапПеревозки":""
				}
			]
		}
}
